postq/__init__.py
postq/__main__.py
postq/enums.py
postq/executors.py
postq/job.py
postq/models.py
postq/q.py
postq/migrations/20211113162456006_init.yaml
postq/migrations/20211113163131659_jobs.yaml
postq/tests/__init__.py
postq/tests/conftest.py
postq/tests/mocks.py
postq/tests/test_executors.py
postq/tests/test_models.py
postq/tests/test_q.py
postq-0.2.8.dist-info/LICENSE
postq-0.2.8.dist-info/METADATA
postq-0.2.8.dist-info/WHEEL
postq-0.2.8.dist-info/entry_points.txt
postq-0.2.8.dist-info/top_level.txt
postq-0.2.8.dist-info/RECORD
