Metadata-Version: 2.1
Name: postq
Version: 0.2.8
Summary: Job queue with DAG workflows, PostgreSQL backend, and choice of job executors.
Home-page: https://github.com/kruxia/postq
Author: Sean Harrison
Author-email: sah@kruxia.com
License: MPL 2.0
Platform: UNKNOWN
Classifier: Development Status :: 3 - Alpha
Classifier: Intended Audience :: Developers
Classifier: License :: OSI Approved :: Mozilla Public License 2.0 (MPL 2.0)
Classifier: Programming Language :: Python :: 3
License-File: LICENSE
Provides-Extra: dev
Provides-Extra: test
